urizen/__init__.py
urizen/core/__init__.py
urizen/core/actor.py
urizen/core/cell.py
urizen/core/entity_collection.py
urizen/core/map.py
urizen/core/metatile.py
urizen/core/thing.py
urizen/core/tile.py
urizen/core/utils.py
urizen/data/__init__.py
urizen/data/themes/__init__.py
urizen/data/themes/gui_theme.json
urizen/data/themes/images/__init__.py
urizen/data/themes/images/gen_explore.png
urizen/data/themes/images/not_implemented.png
urizen/data/tilesets/urizen-onebit-basic/LICENSE
urizen/data/tilesets/urizen-onebit-basic/colored.json
urizen/data/tilesets/urizen-onebit-basic/colored.png
urizen/data/tilesets/urizen-onebit-basic/colored.tsx
urizen/data/tilesets/urizen-onebit-basic/mono.png
urizen/data/tilesets/urizen-onebit-fantasy-medieval/LICENSE
urizen/data/tilesets/urizen-onebit-fantasy-medieval/colored.json
urizen/data/tilesets/urizen-onebit-fantasy-medieval/colored.png
urizen/data/tilesets/urizen-onebit-fantasy-medieval/colored.tsx
urizen/data/tilesets/urizen-onebit-fantasy-medieval/mono.png
urizen/data/tilesets/urizen-onebit-fonts/LICENSE
urizen/data/tilesets/urizen-onebit-fonts/colored.json
urizen/data/tilesets/urizen-onebit-fonts/colored.png
urizen/data/tilesets/urizen-onebit-fonts/colored.tsx
urizen/data/tilesets/urizen-onebit-fonts/mono.png
urizen/data/tilesets/urizen-onebit-modern/LICENSE
urizen/data/tilesets/urizen-onebit-modern/colored.json
urizen/data/tilesets/urizen-onebit-modern/colored.png
urizen/data/tilesets/urizen-onebit-modern/colored.tsx
urizen/data/tilesets/urizen-onebit-modern/mono.png
urizen/generators/__init__.py
urizen/generators/buildings/__init__.py
urizen/generators/buildings/building_bank.py
urizen/generators/buildings/building_house_medieval.py
urizen/generators/buildings/building_housebarn.py
urizen/generators/buildings/building_hunter_robber_house.py
urizen/generators/buildings/building_inn.py
urizen/generators/buildings/building_medieval_mansion.py
urizen/generators/buildings/building_prison.py
urizen-0.2.5.dist-info/LICENSE
urizen-0.2.5.dist-info/METADATA
urizen-0.2.5.dist-info/WHEEL
urizen-0.2.5.dist-info/entry_points.txt
urizen-0.2.5.dist-info/top_level.txt
urizen-0.2.5.dist-info/RECORD
