Metadata-Version: 2.1
Name: urizen
Version: 0.2.5
Summary: Roguelike world generation library
Home-page: https://github.com/vurmux/urizen
Author: Andrey Voronov
Author-email: vurmux@gmail.com
License: Apache
Platform: UNKNOWN
Classifier: Development Status :: 1 - Planning
Classifier: License :: OSI Approved :: Apache Software License
Classifier: Programming Language :: Python :: 3 :: Only
Provides-Extra: dev
Provides-Extra: test
